docling_sdg/__init__.py
docling_sdg/py.typed
docling_sdg/cli/__init__.py
docling_sdg/cli/main.py
docling_sdg/cli/qa.py
docling_sdg/qa/__init__.py
docling_sdg/qa/base.py
docling_sdg/qa/conceptual_generate.py
docling_sdg/qa/critique.py
docling_sdg/qa/generate.py
docling_sdg/qa/sample.py
docling_sdg/qa/utils.py
docling_sdg/qa/prompts/__init__.py
docling_sdg/qa/prompts/critique_prompts.py
docling_sdg/qa/prompts/generation_prompts.py
docling_sdg/resources/__init__.py
docling_sdg/resources/watsonx_example.env
docling_sdg-0.4.0.dist-info/METADATA
docling_sdg-0.4.0.dist-info/WHEEL
docling_sdg-0.4.0.dist-info/entry_points.txt
docling_sdg-0.4.0.dist-info/licenses/LICENSE
docling_sdg-0.4.0.dist-info/RECORD
