Metadata-Version: 2.4
Name: docling-sdg
Version: 0.4.0
Summary: Docling for Synthetic Data Generation (SDG) provides a set of tools to create artificial data from documents, leveraging generative AI and docling's parsing capabilities.
Project-URL: Homepage, https://github.com/docling-project/docling-sdg
Project-URL: Repository, https://github.com/docling-project/docling-sdg
Project-URL: Issues, https://github.com/docling-project/docling-sdg/issues
Project-URL: Changelog, https://github.com/docling-project/docling-sdg/blob/main/CHANGELOG.md
Author-email: Cesar Berrospi Ramis <ceb@zurich.ibm.com>, Rafael Teixeira de Lima <rtdl@ibm.com>, Tim Strohmeyer <Tim.Strohmeyer@ibm.com>, Panos Vagenas <pva@zurich.ibm.com>, Michele Dolfi <dol@zurich.ibm.com>, Peter Staar <taa@zurich.ibm.com>
Maintainer-email: Cesar Berrospi Ramis <ceb@zurich.ibm.com>, Tim Strohmeyer <Tim.Strohmeyer@ibm.com>, Michele Dolfi <dol@zurich.ibm.com>, Peter Staar <taa@zurich.ibm.com>
License-Expression: MIT
License-File: LICENSE
Keywords: AI,artificial intelligence,docling,document understanding,large language models,llm,prompt engineering,sdg,synthetic data generation
Classifier: Development Status :: 4 - Beta
Classifier: Intended Audience :: Developers
Classifier: Intended Audience :: Science/Research
Classifier: Natural Language :: English
Classifier: Operating System :: OS Independent
Classifier: Programming Language :: Python :: 3
Classifier: Programming Language :: Python :: 3.10
Classifier: Programming Language :: Python :: 3.11
Classifier: Programming Language :: Python :: 3.12
Classifier: Topic :: Scientific/Engineering :: Artificial Intelligence
Classifier: Topic :: Scientific/Engineering :: Information Analysis
Classifier: Topic :: Software Development :: Build Tools
Classifier: Topic :: Software Development :: Libraries :: Python Modules
Classifier: Typing :: Typed
Requires-Python: <3.13,>=3.10
Requires-Dist: docling-core[chunking]>=2.23.0
Requires-Dist: docling>=2.26.0
Requires-Dist: llama-index-core>=0.12.25
Requires-Dist: llama-index-embeddings-huggingface>=0.5.5
Requires-Dist: llama-index-llms-ibm>=0.3.3
Requires-Dist: llama-index-llms-openai-like<0.4.0,>=0.3.4
Requires-Dist: pydantic>=2.0.0
Requires-Dist: semchunk>=2.2.2
Requires-Dist: transformers>=4.42.4
Requires-Dist: typer>=0.12.5
Requires-Dist: typing-extensions>=4.12.2
